bayscrape/__init__.py
bayscrape/__main__.py
bayscrape/bsutils.py
bayscrape/color.py
bayscrape/comment.py
bayscrape/details.py
bayscrape/proxies.py
bayscrape/results.py
bayscrape/soup.py
bayscrape-1.1.3.dist-info/LICENSE
bayscrape-1.1.3.dist-info/METADATA
bayscrape-1.1.3.dist-info/WHEEL
bayscrape-1.1.3.dist-info/entry_points.txt
bayscrape-1.1.3.dist-info/top_level.txt
bayscrape-1.1.3.dist-info/RECORD
