Metadata-Version: 2.1
Name: bayscrape
Version: 1.1.3
Summary: Safely browse legal torrents from the comfort of your command-line.
Home-page: https://github.com/mattshu/bayscrape
Author: Matt Kelley
Author-email: mattshu32@gmail.com
License: GNU GPLv3
Platform: UNKNOWN
Classifier: Development Status :: 5 - Production/Stable
Classifier: Environment :: Console
Classifier: Environment :: Win32 (MS Windows)
Classifier: Operating System :: Microsoft :: Windows
Classifier: Operating System :: OS Independent
Classifier: Topic :: Internet
Classifier: Topic :: Terminals
Classifier: Programming Language :: Python :: 3
Classifier: License :: OSI Approved :: GNU General Public License v3 (GPLv3)
Requires-Python: >=3.6
Requires-Dist: requests (>=2.24.0)
Requires-Dist: beautifulsoup4 (>=4.9.3)
Requires-Dist: colored (>=1.4.2)
Requires-Dist: setuptools (>=50.3.2)
Requires-Dist: beautifultable (>=1.0.0)
